Metadata-Version: 2.1
Name: termshot
Version: 0.1
Summary: A python terminal image printer
Home-page: UNKNOWN
Author: Kollob
Author-email: mrtnb1998@gmail.com
License: UNKNOWN
Platform: UNKNOWN
